automation/__init__.py
automation/helpers.py
automation/plugin.py
automation/yamlfile.py
pytest_automation-3.0.0.dist-info/LICENSE
pytest_automation-3.0.0.dist-info/METADATA
pytest_automation-3.0.0.dist-info/WHEEL
pytest_automation-3.0.0.dist-info/entry_points.txt
pytest_automation-3.0.0.dist-info/top_level.txt
pytest_automation-3.0.0.dist-info/RECORD
