Metadata-Version: 2.1
Name: pytest-automation
Version: 3.0.0
Summary: pytest plugin for building a test suite, using YAML files to extend pytest parameterize functionality.
Home-page: https://github.com/asfadmin/Discovery-PytestAutomation
Author: Alaska Satellite Facility Discovery Team
Author-email: uaf-asf-discovery@alaska.edu
License: BSD
Classifier: Framework :: Pytest
Classifier: License :: OSI Approved :: BSD License
Classifier: Operating System :: OS Independent
Classifier: Programming Language :: Python :: 3
Classifier: Programming Language :: Python :: 3 :: Only
Classifier: Programming Language :: Python :: 3.6
Classifier: Programming Language :: Python :: 3.7
Classifier: Programming Language :: Python :: 3.8
Classifier: Programming Language :: Python :: 3.9
Classifier: Topic :: Software Development :: Testing
License-File: LICENSE
Requires-Dist: pytest >=7.0.0
Requires-Dist: PyYAML
